fcomments/.DS_Store
fcomments/__init__.py
fcomments/__main__.py
fcomments/commenter.py
fcomments/dist/tmp7uu5hv2k.whl
fcomments-0.1.3.dist-info/entry_points.txt
fcomments-0.1.3.dist-info/WHEEL
fcomments-0.1.3.dist-info/METADATA
fcomments-0.1.3.dist-info/RECORD
