Metadata-Version: 1.2
Name: fcomments
Version: 0.1.3
Summary: Script for commenting in/out lines in file.
Home-page: https://github.com/tadeoos/fcomments
License: UNKNOWN
Keywords: comments file
Author: Tadek Teleżyński
Author-email: tadekte@gmail.com
Maintainer: tadeo
Maintainer-email: tadekte@gmail.com
Requires-Python: >=3.5
Classifier: Development Status :: 3 - Alpha
Classifier: Programming Language :: Python :: 3
Classifier: Programming Language :: Python :: 3.5
Classifier: Programming Language :: Python :: 3.6
Classifier: Environment :: Console
Classifier: License :: OSI Approved :: MIT License
Classifier: Intended Audience :: Developers
Classifier: Topic :: Software Development :: Pre-processors
Classifier: Topic :: Text Processing :: General
Classifier: Topic :: Utilities
